cacheorm/__init__.py
cacheorm/backends.py
cacheorm/model.py
cacheorm/serializers.py
cacheorm/types.py
cacheorm-0.0.1.dist-info/LICENSE
cacheorm-0.0.1.dist-info/METADATA
cacheorm-0.0.1.dist-info/WHEEL
cacheorm-0.0.1.dist-info/top_level.txt
cacheorm-0.0.1.dist-info/RECORD
