Metadata-Version: 2.1
Name: cacheorm
Version: 0.0.1
Summary: A cache-based python ORM.
Home-page: https://github.com/leosocy/cacheorm
Author: leosocy
Author-email: leosocy@gmail.com
License: MIT
Project-URL: Code, https://github.com/leosocy/cacheorm
Project-URL: Issue tracker, https://github.com/leosocy/cacheorm/issues
Platform: UNKNOWN
Classifier: License :: OSI Approved :: MIT License
Classifier: Programming Language :: Python
Classifier: Programming Language :: Python :: 3
Classifier: Programming Language :: Python :: 3.6
Classifier: Programming Language :: Python :: 3.7
Requires-Python: >=3.6
Provides-Extra: backends
Requires-Dist: redis (>=3.0) ; extra == 'backends'
Requires-Dist: libmc (>=1.3.0) ; extra == 'backends'
Provides-Extra: dev
Requires-Dist: pytest ; extra == 'dev'
Requires-Dist: pytest-cov ; extra == 'dev'
Requires-Dist: mock ; extra == 'dev'
Requires-Dist: coverage ; extra == 'dev'
Requires-Dist: flake8 ; extra == 'dev'
Requires-Dist: mccabe ; extra == 'dev'
Requires-Dist: flake8-bugbear ; extra == 'dev'
Requires-Dist: pep8-naming ; extra == 'dev'
Requires-Dist: redis (>=3.0) ; extra == 'dev'
Requires-Dist: libmc (>=1.3.0) ; extra == 'dev'
Requires-Dist: msgpack (<1.0) ; extra == 'dev'
Requires-Dist: protobuf (>=3.9) ; extra == 'dev'
Provides-Extra: serializers
Requires-Dist: msgpack (<1.0,>=0.6) ; extra == 'serializers'
Requires-Dist: protobuf (>=3.9) ; extra == 'serializers'
